microsoft/teams/a2a/__init__.py
microsoft/teams/a2a/chat_prompt/__init__.py
microsoft/teams/a2a/chat_prompt/agent_client_info.py
microsoft/teams/a2a/chat_prompt/agent_config.py
microsoft/teams/a2a/chat_prompt/plugin.py
microsoft/teams/a2a/chat_prompt/types.py
microsoft/teams/a2a/server/__init__.py
microsoft/teams/a2a/server/a2a_plugin_options.py
microsoft/teams/a2a/server/custom_agent_executor.py
microsoft/teams/a2a/server/logging_middleware.py
microsoft/teams/a2a/server/plugin.py
microsoft_teams_a2a-2.0.0a5.dist-info/METADATA
microsoft_teams_a2a-2.0.0a5.dist-info/WHEEL
microsoft_teams_a2a-2.0.0a5.dist-info/RECORD
