Metadata-Version: 2.4
Name: microsoft-teams-a2a
Version: 2.0.0a5
Summary: plugin that enables your teams agent to be used as an a2a agent
Author-email: Microsoft <TeamsAISDKFeedback@microsoft.com>
License-Expression: MIT
Keywords: agents,ai,bot,microsoft,teams
Requires-Python: <3.14,>=3.12
Requires-Dist: a2a-sdk[core,http-server]>=0.3.7
Requires-Dist: microsoft-teams-ai
Requires-Dist: microsoft-teams-apps
Requires-Dist: microsoft-teams-common
Requires-Dist: pytest>=8.4.1
